invenio_oaiharvester/__init__.py
invenio_oaiharvester/api.py
invenio_oaiharvester/config.py
invenio_oaiharvester/errors.py
invenio_oaiharvester/manage.py
invenio_oaiharvester/models.py
invenio_oaiharvester/utils.py
invenio_oaiharvester/version.py
invenio_oaiharvester/views.py
invenio_oaiharvester/tasks/__init__.py
invenio_oaiharvester/tasks/arxiv.py
invenio_oaiharvester/tasks/records.py
invenio_oaiharvester/templates/oaiharvester/holdingpen/oai_record.html
invenio_oaiharvester/translations/invenio.pot
invenio_oaiharvester/translations/de/LC_MESSAGES/messages.mo
invenio_oaiharvester/translations/de/LC_MESSAGES/messages.po
invenio_oaiharvester/translations/es/LC_MESSAGES/messages.mo
invenio_oaiharvester/translations/es/LC_MESSAGES/messages.po
invenio_oaiharvester/translations/fr/LC_MESSAGES/messages.mo
invenio_oaiharvester/translations/fr/LC_MESSAGES/messages.po
invenio_oaiharvester/translations/it/LC_MESSAGES/messages.mo
invenio_oaiharvester/translations/it/LC_MESSAGES/messages.po
invenio_oaiharvester/upgrades/__init__.py
invenio_oaiharvester/upgrades/oaiharvester_2014_09_09_initial.py
invenio_oaiharvester/upgrades/oaiharvester_2015_07_14_innodb.py
invenio_oaiharvester/workflows/__init__.py
invenio_oaiharvester/workflows/oaiharvest_record.py
invenio_oaiharvester/workflows/oaiharvest_record_approval.py
invenio_oaiharvester-0.1.0.dist-info/DESCRIPTION.rst
invenio_oaiharvester-0.1.0.dist-info/METADATA
invenio_oaiharvester-0.1.0.dist-info/metadata.json
invenio_oaiharvester-0.1.0.dist-info/pbr.json
invenio_oaiharvester-0.1.0.dist-info/RECORD
invenio_oaiharvester-0.1.0.dist-info/top_level.txt
invenio_oaiharvester-0.1.0.dist-info/WHEEL
