Metadata-Version: 2.0
Name: invenio-oaiharvester
Version: 0.1.0
Summary: Invenio module for OAI-PMH metadata harvesting between repositories.
Home-page: https://github.com/inveniosoftware/invenio-oaiharvester
Author: CERN
Author-email: info@invenio-software.org
License: GPLv2
Keywords: invenio oai-pmh harvest metadata
Platform: any
Classifier: Environment :: Web Environment
Classifier: Intended Audience :: Developers
Classifier: License :: OSI Approved :: GNU General Public License v2 (GPLv2)
Classifier: Operating System :: OS Independent
Classifier: Programming Language :: Python
Classifier: Topic :: Internet :: WWW/HTTP :: Dynamic Content
Classifier: Topic :: Software Development :: Libraries :: Python Modules
Classifier: Programming Language :: Python :: 2
Classifier: Programming Language :: Python :: 2.7
Classifier: Development Status :: 1 - Planning
Requires-Dist: Flask (>=0.10.1)
Requires-Dist: six (>=1.7.2)
Requires-Dist: invenio-records (>=0.2.0)
Requires-Dist: sickle (>=0.4)
Provides-Extra: docs
Requires-Dist: Sphinx (>=1.3); extra == 'docs'
Requires-Dist: sphinx-rtd-theme (>=0.1.7); extra == 'docs'
Requires-Dist: mock (==1.0.0); extra == 'docs'
Provides-Extra: tests
Requires-Dist: Flask-Testing (>=0.4.2); extra == 'tests'
Requires-Dist: pytest (>=2.7.0); extra == 'tests'
Requires-Dist: pytest-cov (>=1.8.0); extra == 'tests'
Requires-Dist: pytest-pep8 (>=1.0.6); extra == 'tests'
Requires-Dist: coverage (>=3.7.1); extra == 'tests'
Requires-Dist: httpretty (>=0.8.3); extra == 'tests'
